pulumi_meraki/__init__.py
pulumi_meraki/_utilities.py
pulumi_meraki/get_devices.py
pulumi_meraki/get_networks.py
pulumi_meraki/get_organizations.py
pulumi_meraki/outputs.py
pulumi_meraki/provider.py
pulumi_meraki/pulumi-plugin.json
pulumi_meraki/py.typed
pulumi_meraki/administered/__init__.py
pulumi_meraki/administered/_inputs.py
pulumi_meraki/administered/get_identities_me.py
pulumi_meraki/administered/get_licensing_subscription_entitlements.py
pulumi_meraki/administered/get_licensing_subscription_subscriptions.py
pulumi_meraki/administered/get_licensing_subscription_subscriptions_compliance_statuses.py
pulumi_meraki/administered/licensing_subscription_subscriptions_bind.py
pulumi_meraki/administered/licensing_subscription_subscriptions_claim.py
pulumi_meraki/administered/licensing_subscription_subscriptions_claim_key_validate.py
pulumi_meraki/administered/outputs.py
pulumi_meraki/config/__init__.py
pulumi_meraki/config/__init__.pyi
pulumi_meraki/config/vars.py
pulumi_meraki/devices/__init__.py
pulumi_meraki/devices/_inputs.py
pulumi_meraki/devices/appliance_radio_settings.py
pulumi_meraki/devices/appliance_uplinks_settings.py
pulumi_meraki/devices/appliance_vmx_authentication_token.py
pulumi_meraki/devices/base.py
pulumi_meraki/devices/blink_leds.py
pulumi_meraki/devices/camera_custom_analytics.py
pulumi_meraki/devices/camera_generate_snapshot.py
pulumi_meraki/devices/camera_quality_and_retention.py
pulumi_meraki/devices/camera_sense.py
pulumi_meraki/devices/camera_video_settings.py
pulumi_meraki/devices/camera_wireless_profiles.py
pulumi_meraki/devices/cellular_gateway_lan.py
pulumi_meraki/devices/cellular_gateway_port_forwarding_rules.py
pulumi_meraki/devices/cellular_sims.py
pulumi_meraki/devices/get_appliance_performance.py
pulumi_meraki/devices/get_appliance_radio_settings.py
pulumi_meraki/devices/get_appliance_uplinks_settings.py
pulumi_meraki/devices/get_camera_analytics_live.py
pulumi_meraki/devices/get_camera_custom_analytics.py
pulumi_meraki-0.4.5.dist-info/METADATA
pulumi_meraki-0.4.5.dist-info/WHEEL
pulumi_meraki-0.4.5.dist-info/top_level.txt
pulumi_meraki-0.4.5.dist-info/RECORD
